{
  "person": "Mom",
  "set": "dad",
  "questionId": "warning-courier",
  "question": "For the half-hour warning, did you want to ask to see proof from the courier before trusting the letter?",
  "answer": "I really don't understand that.",
  "chapter": "",
  "recordedAt": "2026-05-18T17:34:44.492Z",
  "receivedAt": "2026-05-18T17:34:44.636Z",
  "sourceUrl": "https://shukri.net/#family",
  "userAgent": "Mozilla/5.0 (Macintosh; Intel Mac OS X 10_15_7) AppleWebKit/537.36 (KHTML, like Gecko) Chrome/148.0.0.0 Safari/537.36"
}